README.md
setup.py
azdvop/AzDevOps.py
azdvop/__init__.py
pyazdvop.egg-info/PKG-INFO
pyazdvop.egg-info/SOURCES.txt
pyazdvop.egg-info/dependency_links.txt
pyazdvop.egg-info/not-zip-safe
pyazdvop.egg-info/requires.txt
pyazdvop.egg-info/top_level.txt