Metadata-Version: 1.1
Name: pyazdvop
Version: 1.0.1
Summary: Library for Azure DevOps API for Python
Home-page: https://github.com/rockraft7/pyazdevops
Author: M Faizal Sidek
Author-email: mfaizal.sidek@petronas.com.my
License: MIT
Keywords: Azure,DevOps,Python,API
Platform: UNKNOWN
Classifier: Development Status :: 3 - Alpha
Classifier: Intended Audience :: Developers
Classifier: Topic :: Software Development :: Libraries
Classifier: License :: OSI Approved :: MIT License
Classifier: Programming Language :: Python :: 2.7
